persian_sentiment/__init__.py
persian_sentiment/analyzer.py
persian_sentiment-0.1.0.dist-info/licenses/LICENSE.txt
persian_sentiment-0.1.0.dist-info/METADATA
persian_sentiment-0.1.0.dist-info/WHEEL
persian_sentiment-0.1.0.dist-info/top_level.txt
persian_sentiment-0.1.0.dist-info/RECORD
